{
  "users": [
    {
      "id": 1,
      "name": "Test Testerson",
      "email": "test@test.com"
    },
    {
      "email": "one@one.com",
      "name": "One Onederson",
      "id": 2
    },
    {
      "email": "aja@aja.com",
      "name": "Aja Washington",
      "id": 3
    }
  ],
  "artists": [
    {
      "id": 1,
      "name": "Melinda Talbert"
    },
    {
      "id": 2,
      "name": "Rustin Pynch"
    }
  ],
  "tours": [
    {
      "id": 1,
      "userId": 1,
      "name": "You Clean Up My Mess Tour 2021",
      "dateStart": "5/1/2021",
      "dateEnd": "5/31/2021"
    },
    {
      "id": 2,
      "name": "Let Your Best People Go During the Pandemic Tour 2020",
      "dateStart": "7/1/2021",
      "dateEnd": "7/31/2021",
      "artistId": 1,
      "userId": 1
    },
    {
      "id": 3,
      "name": "My Smile is Amazing 2021",
      "dateStart": "5/1/2021",
      "dateEnd": "6/30/2021",
      "artistId": 2,
      "userId": 2
    },
    {
      "id": 4,
      "name": "Lots of Covers in My Set 2021",
      "dateStart": "7/10/2021",
      "dateEnd": "8/20/2021",
      "artistId": 2,
      "userId": 2
    },
    {
      "id": 5,
      "userId": 1,
      "name": "Another Tour Just Like the Last One 2021",
      "dateStart": "4/1/21",
      "dateEnd": "4/30/21"
    },
    {
      "userId": 3,
      "name": "123",
      "dateStart": "456",
      "dateEnd": "789",
      "id": 6
    }
  ],
  "crewTypes": [
    {
      "id": 1,
      "name": "Band"
    },
    {
      "id": 2,
      "name": "Production"
    },
    {
      "id": 3,
      "name": "Audio"
    },
    {
      "id": 4,
      "name": "Stage/Rigging"
    },
    {
      "id": 5,
      "name": "Video"
    },
    {
      "id": 6,
      "name": "Lighting"
    },
    {
      "id": 7,
      "name": "Rigging"
    },
    {
      "id": 8,
      "name": "Drivers"
    },
    {
      "id": 9,
      "name": "Backline"
    }
  ],
  "crew": [
    {
      "id": 2,
      "firstName": "Reginald",
      "lastName": "Lake",
      "title": "TM",
      "crewTypeId": 2,
      "available": true
    },
    {
      "id": 3,
      "firstName": "Lee",
      "lastName": "Dotson",
      "crewTypeId": 2,
      "title": "PM",
      "available": true
    },
    {
      "id": 4,
      "firstName": "Rahim",
      "lastName": "Castillo",
      "crewTypeId": 2,
      "title": "Asst TM",
      "available": true
    },
    {
      "id": 5,
      "firstName": "Catrin",
      "lastName": "Pemberton",
      "title": "PA",
      "crewTypeId": 2,
      "available": true
    },
    {
      "id": 6,
      "firstName": "Dale",
      "lastName": "Beil",
      "title": "Merch",
      "crewTypeId": 2,
      "available": true
    },
    {
      "id": 7,
      "firstName": "Roy",
      "lastName": "Hamer",
      "crewTypeId": 2,
      "title": "Security",
      "available": true
    },
    {
      "id": 8,
      "firstName": "Asia",
      "lastName": "Davidson",
      "title": "Guitar",
      "crewTypeId": 1,
      "available": true
    },
    {
      "id": 9,
      "firstName": "Siyana",
      "lastName": "Curry",
      "title": "Guitar 2",
      "crewTypeId": 1,
      "available": true
    },
    {
      "id": 10,
      "firstName": "Zayn",
      "lastName": "Pugh",
      "crewTypeId": 1,
      "title": "Steel",
      "available": true
    },
    {
      "id": 11,
      "firstName": "Amy",
      "lastName": "Tyson",
      "crewTypeId": 1,
      "title": "Keys",
      "available": true
    },
    {
      "id": 12,
      "firstName": "Herbert",
      "lastName": "Sharp",
      "crewTypeId": 1,
      "title": "Bass",
      "available": true
    },
    {
      "id": 13,
      "firstName": "Ranveer",
      "lastName": "Wu",
      "title": "Drums",
      "crewTypeId": 1,
      "available": true
    },
    {
      "id": 16,
      "firstName": "Bob",
      "lastName": "Crew Guy",
      "title": "Tech",
      "crewTypeId": 6,
      "available": true
    },
    {
      "id": 18,
      "firstName": "Blu",
      "lastName": "Sanders",
      "title": "111",
      "crewTypeId": 6,
      "available": false
    },
    {
      "firstName": "Blu",
      "lastName": "Sanders",
      "title": "Tech",
      "available": true,
      "crewTypeId": 6,
      "id": 19
    }
  ],
  "tourRun": [
    {
      "name": "Nash - Indy - Chicago",
      "description": "",
      "dateStart": "1/1/20",
      "dateEnd": "1/5/20",
      "timeLeave": "11p",
      "timeArrive": "10a",
      "tourId": 2,
      "perDiem": 25,
      "daysOut": 5,
      "d100": "0",
      "d50": "0",
      "d20": "*",
      "d10": "*",
      "d5": "*",
      "d1": "*",
      "id": 1
    },
    {
      "name": "ATL - Charlotte - Greenville",
      "description": "",
      "dateStart": "1/1/20",
      "dateEnd": "1/5/20",
      "timeLeave": "11p",
      "timeArrive": "10a",
      "tourId": 4,
      "perDiem": 25,
      "daysOut": 6,
      "d100": "0",
      "d50": "0",
      "d20": "5",
      "d10": "*",
      "d5": "*",
      "d1": "*",
      "id": 2
    },
    {
      "id": 3,
      "name": "Hou - Dal - Aus",
      "description": "",
      "dateStart": "1/1/20",
      "dateEnd": "1/5/20",
      "timeLeave": "11p",
      "timeArrive": "10a",
      "tourId": 3,
      "perDiem": 25,
      "daysOut": 5,
      "d100": "0",
      "d50": "0",
      "d20": "4",
      "d10": "*",
      "d5": "*",
      "d1": "*"
    },
    {
      "name": "SAN - LA -SAC",
      "description": "",
      "dateStart": "1/1/20",
      "dateEnd": "1/5/20",
      "timeLeave": "11p",
      "timeArrive": "10a",
      "tourId": 2,
      "perDiem": 35,
      "daysOut": 13,
      "d100": "0",
      "d50": "1",
      "d20": "15",
      "d10": "8",
      "d5": "*",
      "d1": "*",
      "id": 4
    },
    {
      "name": "Portland - Seattle -Vancouver",
      "description": "",
      "dateStart": "1/1/20",
      "dateEnd": "1/5/20",
      "timeLeave": "11p",
      "timeArrive": "11a",
      "tourId": 2,
      "perDiem": 35,
      "daysOut": 8,
      "d100": "0",
      "d50": "0",
      "d20": "10",
      "d10": "*",
      "d5": "*",
      "d1": "*",
      "id": 6
    },
    {
      "name": "123",
      "description": "",
      "dateStart": "456",
      "dateEnd": "789",
      "timeLeave": "000",
      "timeArrive": "",
      "tourId": 6,
      "perDiem": 25,
      "daysOut": 13,
      "d100": "0",
      "d50": "0",
      "d20": "10",
      "d10": "8",
      "d5": "*",
      "d1": "*",
      "id": 8
    },
    {
      "name": "Boston - NYC - DC",
      "description": "",
      "dateStart": "1/1/20",
      "dateEnd": "1/5/20",
      "timeLeave": "11p",
      "timeArrive": "11a",
      "tourId": 2,
      "perDiem": 35,
      "daysOut": 9,
      "d100": "0",
      "d50": "1",
      "d20": "8",
      "d10": "8",
      "d5": "*",
      "d1": "*",
      "id": 9
    }
  ],
  "tourRunCrew": []
}